MANIFEST.in
l10n_fr_hr_payroll_data.xml
l10n_fr_hr_payroll_view.xml
setup.py
./__init__.py
./__openerp__.py
./l10n_fr_hr_payroll.py
./report/__init__.py
./report/fiche_paye.py
openerp_l10n_fr_hr_payroll.egg-info/PKG-INFO
openerp_l10n_fr_hr_payroll.egg-info/SOURCES.txt
openerp_l10n_fr_hr_payroll.egg-info/dependency_links.txt
openerp_l10n_fr_hr_payroll.egg-info/requires.txt
openerp_l10n_fr_hr_payroll.egg-info/top_level.txt
report/fiche_paye.rml